<?xml version="1.0" encoding="UTF-8"?>
<packet id="SM_EX_TODO_LIST_RECOMMAND" xmlns="http://www.l2emu-unique.net" xmlns:xsi="http://www.w3.org/2001/XMLSchema-instance" xsi:schemaLocation="http://www.l2emu-unique.net ../../../schemata/packet.xsd">
	<word alias="Events" id="cnt" />
	<loop id="cnt">
		<byte alias="Tab" type="daily.TodoListTab" />
		<string alias="HTML name" />
		<string alias="Event" />
		<word alias="Min hours" />
		<word alias="Max hours" />
		<word alias="Min level" />
		<word alias="Max level" />
		<byte alias="Progress" type="daily.EventProgress" />
		<byte alias="" />
	</loop>
</packet>