<?xml version="1.0" encoding="UTF-8"?>
<!-- Augmentation effect WORDs are now DWORDs -->
<packet id="SM_SHORT_CUT_REGISTER" xmlns="http://www.l2emu-unique.net" xmlns:xsi="http://www.w3.org/2001/XMLSchema-instance" xsi:schemaLocation="http://www.l2emu-unique.net ../../../schemata/packet.xsd">
	<dword alias="Type" type="shortcut.ShortcutType" id="cond_1" />
	<dword alias="Slot" type="shortcut.ShortcutSlotBase12" />
	<branch id="cond_1" condition="shortcut.ItemShortcut">
		<dword alias="Item OID" type="ObjectID" />
	</branch>
	<branch id="cond_1" condition="shortcut.SkillShortcut">
		<dword alias="Skill" type="Skill">
			<scriptAlias id="__INTERP_CORRECTION_SKILL_ID" />
		</dword>
		<dword alias="Level" type="skill.SkillLevel">
			<scriptAlias id="__INTERP_CORRECTION_SKILL_LEVEL" />
		</dword>
		<dword alias="Cooldown group" />
		<byte alias="Disabled" type="YesOrNo" />
	</branch>
	<branch id="cond_1" condition="shortcut.ActionShortcut">
		<dword alias="Action" type="PlayerAction" />
	</branch>
	<branch id="cond_1" condition="shortcut.MacroShortcut">
		<dword alias="Macro ID" />
	</branch>
	<branch id="cond_1" condition="shortcut.RecipeShortcut">
		<dword alias="Recipe" type="Recipe" />
	</branch>
	<branch id="cond_1" condition="shortcut.DefaultShortcut">
		<dword alias="ID" />
	</branch>
	<dword alias="Executor" type="shortcut.ShortcutActor" />
	<branch id="cond_1" condition="shortcut.ItemShortcut">
		<dword alias="Cooldown group" />
		<dword alias="Remaining time" type="TimeRemaining" />
		<dword alias="Cooldown time" type="TimeRemaining" />
		<dword alias="Augmentation effect (1)" type="Augmentation" /> <!-- NEW -->
		<dword alias="Augmentation effect (2)" type="Augmentation" /> <!-- NEW -->
		<dword alias="0" />
	</branch>
	
	<!-- NEW -->
	<branch id="cond_1" condition="shortcut.SkillShortcut">
		<dword alias="0" />
		<dword alias="0/2/4" /> <!-- noblesse blessing/strider siege ass/summon siege golem = 4, earthquake/backstab = 2 -->
	</branch>
</packet>